{"resource":"commonplayerinfo","parameters":[{"PlayerID":1885},{"LeagueID":"00"}],"resultSets":[{"name":"CommonPlayerInfo","headers":["PERSON_ID","FIRST_NAME","LAST_NAME","DISPLAY_FIRST_LAST","DISPLAY_LAST_COMMA_FIRST","DISPLAY_FI_LAST","BIRTHDATE","SCHOOL","COUNTRY","LAST_AFFILIATION","HEIGHT","WEIGHT","SEASON_EXP","JERSEY","POSITION","ROSTERSTATUS","TEAM_ID","TEAM_NAME","TEAM_ABBREVIATION","TEAM_CODE","TEAM_CITY","PLAYERCODE","FROM_YEAR","TO_YEAR","DLEAGUE_FLAG","GAMES_PLAYED_FLAG","DRAFT_YEAR","DRAFT_ROUND","DRAFT_NUMBER"],"rowSet":[[1885,"Lamar","Odom","Lamar Odom","Odom, Lamar","L. Odom","1979-11-06T00:00:00","Rhode Island","USA","Rhode Island/USA","6-10","230",14,"","Forward","Active",1610612747,"Lakers","LAL","lakers","Los Angeles","lamar_odom",1999,2013,"N","Y","1999","1","4"]]},{"name":"PlayerHeadlineStats","headers":["PLAYER_ID","PLAYER_NAME","TimeFrame","PTS","AST","REB","ALL_STAR_APPEARANCES"],"rowSet":[[1885,"Lamar Odom","career",13.3,3.7,8.4,0]]},{"name":"AvailableSeasons","headers":["SEASON_ID"],"rowSet":[["11999"],["21999"],["12000"],["22000"],["12001"],["22001"],["22002"],["12003"],["22003"],["42003"],["12004"],["22004"],["12005"],["22005"],["42005"],["12006"],["22006"],["42006"],["22007"],["42007"],["12008"],["22008"],["42008"],["12009"],["22009"],["42009"],["12010"],["22010"],["42010"],["12011"],["22011"],["12012"],["22012"],["42012"]]}]}