{"resource":"commonplayerinfo","parameters":[{"PlayerID":739},{"LeagueID":"00"}],"resultSets":[{"name":"CommonPlayerInfo","headers":["PERSON_ID","FIRST_NAME","LAST_NAME","DISPLAY_FIRST_LAST","DISPLAY_LAST_COMMA_FIRST","DISPLAY_FI_LAST","BIRTHDATE","SCHOOL","COUNTRY","LAST_AFFILIATION","HEIGHT","WEIGHT","SEASON_EXP","JERSEY","POSITION","ROSTERSTATUS","TEAM_ID","TEAM_NAME","TEAM_ABBREVIATION","TEAM_CODE","TEAM_CITY","PLAYERCODE","FROM_YEAR","TO_YEAR","DLEAGUE_FLAG","GAMES_PLAYED_FLAG","DRAFT_YEAR","DRAFT_ROUND","DRAFT_NUMBER"],"rowSet":[[739,"Rasheed","Wallace","Rasheed Wallace","Wallace, Rasheed","R. Wallace","1974-09-17T00:00:00","North Carolina","USA","North Carolina/USA","","",15,"","","Inactive",0,"","","","","rasheed_wallace",1995,2012,"N","Y","1995","1","4"]]},{"name":"PlayerHeadlineStats","headers":["PLAYER_ID","PLAYER_NAME","TimeFrame","PTS","AST","REB","ALL_STAR_APPEARANCES"],"rowSet":[[739,"Rasheed Wallace","career",14.4,1.8,6.7,4]]},{"name":"AvailableSeasons","headers":["SEASON_ID"],"rowSet":[["21995"],["21996"],["41996"],["11997"],["21997"],["41997"],["11998"],["21998"],["41998"],["11999"],["21999"],["31999"],["41999"],["12000"],["22000"],["32000"],["42000"],["12001"],["22001"],["42001"],["12002"],["22002"],["42002"],["12003"],["22003"],["42003"],["12004"],["22004"],["42004"],["12005"],["22005"],["32005"],["42005"],["12006"],["22006"],["42006"],["12007"],["22007"],["32007"],["42007"],["12008"],["22008"],["42008"],["12009"],["22009"],["42009"],["22012"]]}]}