{"resource":"commonplayerinfo","parameters":[{"PlayerID":96},{"LeagueID":"00"}],"resultSets":[{"name":"CommonPlayerInfo","headers":["PERSON_ID","FIRST_NAME","LAST_NAME","DISPLAY_FIRST_LAST","DISPLAY_LAST_COMMA_FIRST","DISPLAY_FI_LAST","BIRTHDATE","SCHOOL","COUNTRY","LAST_AFFILIATION","HEIGHT","WEIGHT","SEASON_EXP","JERSEY","POSITION","ROSTERSTATUS","TEAM_ID","TEAM_NAME","TEAM_ABBREVIATION","TEAM_CODE","TEAM_CITY","PLAYERCODE","FROM_YEAR","TO_YEAR","DLEAGUE_FLAG","GAMES_PLAYED_FLAG","DRAFT_YEAR","DRAFT_ROUND","DRAFT_NUMBER"],"rowSet":[[96,"Detlef","Schrempf","Detlef Schrempf","Schrempf, Detlef","D. Schrempf","1963-01-21T00:00:00","Washington","USA","Washington/USA","6-10","235",15,"12","Forward","Active",1610612760,"SuperSonics","SEA","thunder","Seattle","detlef_schrempf",1985,2000,"N","Y","1985","1","8"]]},{"name":"PlayerHeadlineStats","headers":["PLAYER_ID","PLAYER_NAME","TimeFrame","PTS","AST","REB","ALL_STAR_APPEARANCES"],"rowSet":[[96,"Detlef Schrempf","career",13.9,3.4,6.2,3]]},{"name":"AvailableSeasons","headers":["SEASON_ID"],"rowSet":[["21985"],["41985"],["21986"],["41986"],["21987"],["41987"],["21988"],["21989"],["41989"],["21990"],["41990"],["21991"],["41991"],["21992"],["31992"],["41992"],["21993"],["41993"],["21994"],["31994"],["41994"],["21995"],["41995"],["21996"],["31996"],["41996"],["11997"],["21997"],["41997"],["11998"],["21998"],["11999"],["21999"],["41999"],["22000"],["42000"]]}]}