{"resource":"boxscore","parameters":{"GameID":"0041500306","StartPeriod":1,"EndPeriod":10,"StartRange":0,"EndRange":28800,"RangeType":0},"resultSets":[{"name":"PlayerStats","headers":["GAME_ID","TEAM_ID","TEAM_ABBREVIATION","TEAM_CITY","PLAYER_ID","PLAYER_NAME","START_POSITION","COMMENT","MIN","FGM","FGA","FG_PCT","FG3M","FG3A","FG3_PCT","FTM","FTA","FT_PCT","OREB","DREB","REB","AST","STL","BLK","TO","PF","PTS","PLUS_MINUS"],"rowSet":[["0041500306",1610612739,"CLE","Cleveland",2544,"LeBron James","F","","40:57",13,22,0.591,3,6,0.5,4,7,0.571,2,9,11,6,1,3,3,2,33,22],["0041500306",1610612739,"CLE","Cleveland",201567,"Kevin Love","F","","38:58",5,11,0.455,4,8,0.5,6,6,1,0,12,12,4,0,0,0,2,20,22],["0041500306",1610612739,"CLE","Cleveland",202684,"Tristan Thompson","C","","24:01",1,1,1,0,0,0,0,0,0,2,3,5,0,0,0,1,4,2,11],["0041500306",1610612739,"CLE","Cleveland",2747,"JR Smith","G","","36:27",5,9,0.556,5,8,0.625,0,0,0,0,0,0,1,1,1,0,2,15,22],["0041500306",1610612739,"CLE","Cleveland",202681,"Kyrie Irving","G","","39:53",12,24,0.5,2,4,0.5,4,5,0.8,0,4,4,9,3,1,4,1,30,21],["0041500306",1610612739,"CLE","Cleveland",101112,"Channing Frye","","","14:52",2,3,0.667,2,3,0.667,0,0,0,0,1,1,0,0,1,0,4,6,6],["0041500306",1610612739,"CLE","Cleveland",2210,"Richard Jefferson","","","12:22",1,1,1,1,1,1,0,0,0,0,1,1,0,0,0,0,0,3,6],["0041500306",1610612739,"CLE","Cleveland",202697,"Iman Shumpert","","","18:12",0,0,0,0,0,0,0,0,0,0,3,3,0,1,0,0,2,0,14],["0041500306",1610612739,"CLE","Cleveland",203521,"Matthew Dellavedova","","","9:02",1,2,0.5,0,1,0,2,3,0.667,0,1,1,2,0,0,2,1,4,4],["0041500306",1610612739,"CLE","Cleveland",2592,"James Jones","","","2:38",0,0,0,0,0,0,0,0,0,0,0,0,0,0,0,0,0,0,1],["0041500306",1610612739,"CLE","Cleveland",2563,"Dahntay Jones","","","2:38",0,1,0,0,0,0,0,0,0,0,0,0,0,0,0,0,0,0,1],["0041500306",1610612739,"CLE","Cleveland",202389,"Timofey Mozgov","","DNP - Coach's Decision                  ",null,null,null,null,null,null,null,null,null,null,null,null,null,null,null,null,null,null,null,null],["0041500306",1610612739,"CLE","Cleveland",2590,"Mo Williams","","DNP - Coach's Decision                  ",null,null,null,null,null,null,null,null,null,null,null,null,null,null,null,null,null,null,null,null],["0041500306",1610612761,"TOR","Toronto",201960,"DeMarre Carroll","F","","28:13",3,9,0.333,1,2,0.5,0,0,0,2,4,6,0,0,0,1,3,7,-16],["0041500306",1610612761,"TOR","Toronto",2449,"Luis Scola","F","","5:33",0,1,0,0,1,0,0,0,0,0,0,0,0,0,0,1,1,0,-7],["0041500306",1610612761,"TOR","Toronto",202687,"Bismack Biyombo","C","","26:10",1,4,0.25,0,0,0,2,4,0.5,0,9,9,0,1,1,1,2,4,-25],["0041500306",1610612761,"TOR","Toronto",201942,"DeMar DeRozan","G","","41:56",9,18,0.5,0,1,0,2,2,1,0,3,3,4,0,0,4,4,20,-24],["0041500306",1610612761,"TOR","Toronto",200768,"Kyle Lowry","G","","42:19",11,22,0.5,6,12,0.5,7,7,1,1,2,3,3,0,1,2,2,35,-30],["0041500306",1610612761,"TOR","Toronto",202335,"Patrick Patterson","","","34:37",3,9,0.333,1,5,0.2,2,4,0.5,0,1,1,2,1,0,1,4,9,-12],["0041500306",1610612761,"TOR","Toronto",202685,"Jonas Valanciunas","","","17:21",3,5,0.6,0,0,0,0,0,0,4,4,8,1,0,0,0,0,6,4],["0041500306",1610612761,"TOR","Toronto",202709,"Cory Joseph","","","13:17",1,3,0.333,0,1,0,0,0,0,0,0,0,0,2,0,0,1,2,-4],["0041500306",1610612761,"TOR","Toronto",203082,"Terrence Ross","","","7:45",0,1,0,0,1,0,0,0,0,0,0,0,0,1,0,0,0,0,-5],["0041500306",1610612761,"TOR","Toronto",201949,"James Johnson","","","14:55",1,4,0.25,0,1,0,0,0,0,0,1,1,0,0,0,2,2,2,-8],["0041500306",1610612761,"TOR","Toronto",1626181,"Norman Powell","","","2:38",1,2,0.5,0,1,0,0,0,0,0,1,1,0,1,0,0,0,2,-1],["0041500306",1610612761,"TOR","Toronto",1626153,"Delon Wright","","","2:38",0,1,0,0,0,0,0,0,0,0,0,0,0,0,0,0,0,0,-1],["0041500306",1610612761,"TOR","Toronto",201574,"Jason Thompson","","","2:38",0,0,0,0,0,0,0,0,0,0,1,1,0,0,0,0,0,0,-1]]},{"name":"TeamStats","headers":["GAME_ID","TEAM_ID","TEAM_NAME","TEAM_ABBREVIATION","TEAM_CITY","MIN","FGM","FGA","FG_PCT","FG3M","FG3A","FG3_PCT","FTM","FTA","FT_PCT","OREB","DREB","REB","AST","STL","BLK","TO","PF","PTS","PLUS_MINUS"],"rowSet":[["0041500306",1610612761,"Raptors","TOR","Toronto","240:00",33,79,0.418,8,25,0.32,13,17,0.765,7,26,33,10,6,2,12,19,87,-26],["0041500306",1610612739,"Cavaliers","CLE","Cleveland","240:00",40,74,0.541,17,31,0.548,16,21,0.762,4,34,38,22,6,6,10,18,113,26]]},{"name":"TeamStarterBenchStats","headers":["GAME_ID","TEAM_ID","TEAM_NAME","TEAM_ABBREVIATION","TEAM_CITY","STARTERS_BENCH","MIN","FGM","FGA","FG_PCT","FG3M","FG3A","FG3_PCT","FTM","FTA","FT_PCT","OREB","DREB","REB","AST","STL","BLK","TO","PF","PTS"],"rowSet":[["0041500306",1610612761,"Raptors","TOR","Toronto","Starters","144:11",24,54,0.444,7,16,0.438,11,13,0.846,3,18,21,7,1,2,9,12,66],["0041500306",1610612761,"Raptors","TOR","Toronto","Bench","95:49",9,25,0.36,1,9,0.111,2,4,0.5,4,8,12,3,5,0,3,7,21],["0041500306",1610612739,"Cavaliers","CLE","Cleveland","Starters","180:16",36,67,0.537,14,26,0.538,14,18,0.778,4,28,32,20,5,5,8,11,100],["0041500306",1610612739,"Cavaliers","CLE","Cleveland","Bench","59:44",4,7,0.571,3,5,0.6,2,3,0.667,0,6,6,2,1,1,2,7,13]]}]}