{"resource":"gamelogs","parameters":{"MeasureType":"Base","PerMode":"Totals","LeagueID":"00","SeasonYear":"1987-88","SeasonType":"Playoffs","PORound":0,"TeamID":null,"PlayerID":2,"Outcome":null,"Location":null,"Month":0,"SeasonSegment":null,"DateFrom":null,"DateTo":null,"OppTeamID":0,"VsConference":null,"VsDivision":null,"GameSegment":null,"Period":0,"ShotClockRange":null,"LastNGames":0},"resultSets":[{"name":"PlayerGameLogs","headers":["SEASON_ID","PLAYER_ID","PLAYER_NAME","TEAM_ID","TEAM_ABBREVIATION","TEAM_NAME","GAME_ID","GAME_DATE","MATCHUP","WL","MIN","FGM","FGA","FG_PCT","FG3M","FG3A","FG3_PCT","FTM","FTA","FT_PCT","OREB","DREB","REB","AST","STL","BLK","TOV","PF","PTS","PLUS_MINUS","VIDEO_AVAILABLE"],"rowSet":[["41987",2,"Byron Scott",1610612747,"LAL","Los Angeles Lakers","0048700080","1988-06-21","LAL vs. DET","W",37,7,12,0.583,1,3,0.333,6,6,1,0,3,3,0,1,0,3,2,21,null,0],["41987",2,"Byron Scott",1610612747,"LAL","Los Angeles Lakers","0048700079","1988-06-19","LAL vs. DET","W",35,7,12,0.583,0,0,null,2,4,0.5,2,5,7,3,1,1,1,1,16,null,0],["41987",2,"Byron Scott",1610612747,"LAL","Los Angeles Lakers","0048700078","1988-06-16","LAL @ DET","L",44,6,16,0.375,1,1,1,2,5,0.4,2,3,5,2,3,0,2,3,15,null,0],["41987",2,"Byron Scott",1610612747,"LAL","Los Angeles Lakers","0048700077","1988-06-14","LAL @ DET","L",37,6,14,0.429,0,1,0,1,1,1,0,5,5,2,0,2,5,4,13,null,0],["41987",2,"Byron Scott",1610612747,"LAL","Los Angeles Lakers","0048700076","1988-06-12","LAL @ DET","W",38,6,13,0.462,1,1,1,5,5,1,0,2,2,1,0,0,1,3,18,null,0],["41987",2,"Byron Scott",1610612747,"LAL","Los Angeles Lakers","0048700075","1988-06-09","LAL vs. DET","W",44,8,14,0.571,2,3,0.667,6,8,0.75,0,6,6,3,1,0,0,3,24,null,0],["41987",2,"Byron Scott",1610612747,"LAL","Los Angeles Lakers","0048700074","1988-06-07","LAL vs. DET","L",46,10,24,0.417,0,2,0,5,6,0.833,4,2,6,3,1,0,3,5,25,null,0],["41987",2,"Byron Scott",1610612747,"LAL","Los Angeles Lakers","0048700073","1988-06-04","LAL vs. DAL","W",38,6,13,0.462,2,3,0.667,7,7,1,0,0,0,5,1,0,1,1,21,null,0],["41987",2,"Byron Scott",1610612747,"LAL","Los Angeles Lakers","0048700071","1988-06-02","LAL @ DAL","L",37,9,14,0.643,0,2,0,9,9,1,3,3,6,3,0,0,0,3,27,null,0],["41987",2,"Byron Scott",1610612747,"LAL","Los Angeles Lakers","0048700069","1988-05-31","LAL vs. DAL","W",41,7,12,0.583,1,1,1,2,2,1,0,6,6,1,0,0,3,1,17,null,0],["41987",2,"Byron Scott",1610612747,"LAL","Los Angeles Lakers","0048700067","1988-05-29","LAL @ DAL","L",32,4,7,0.571,0,1,0,2,2,1,3,3,6,1,1,1,1,4,10,null,0],["41987",2,"Byron Scott",1610612747,"LAL","Los Angeles Lakers","0048700065","1988-05-27","LAL @ DAL","L",39,4,13,0.308,0,1,0,3,3,1,0,3,3,4,2,0,1,0,11,null,0],["41987",2,"Byron Scott",1610612747,"LAL","Los Angeles Lakers","0048700062","1988-05-25","LAL vs. DAL","W",43,11,17,0.647,1,3,0.333,7,7,1,0,1,1,5,4,0,2,3,30,null,0],["41987",2,"Byron Scott",1610612747,"LAL","Los Angeles Lakers","0048700061","1988-05-23","LAL vs. DAL","W",42,7,14,0.5,2,3,0.667,7,8,0.875,1,1,2,7,4,0,0,1,23,null,0],["41987",2,"Byron Scott",1610612747,"LAL","Los Angeles Lakers","0048700059","1988-05-21","LAL vs. UTH","W",40,12,19,0.632,1,5,0.2,4,5,0.8,0,5,5,0,3,0,1,4,29,null,0],["41987",2,"Byron Scott",1610612747,"LAL","Los Angeles Lakers","0048700056","1988-05-19","LAL @ UTH","L",34,5,16,0.313,2,2,1,4,4,1,1,3,4,1,0,1,1,3,16,null,0],["41987",2,"Byron Scott",1610612747,"LAL","Los Angeles Lakers","0048700053","1988-05-17","LAL vs. UTH","W",41,10,21,0.476,3,4,0.75,1,2,0.5,0,6,6,4,1,0,2,4,24,null,0],["41987",2,"Byron Scott",1610612747,"LAL","Los Angeles Lakers","0048700047","1988-05-15","LAL @ UTH","W",38,7,19,0.368,1,5,0.2,5,6,0.833,0,3,3,2,4,0,2,2,20,null,0],["41987",2,"Byron Scott",1610612747,"LAL","Los Angeles Lakers","0048700043","1988-05-13","LAL @ UTH","L",38,14,23,0.609,1,3,0.333,0,0,null,3,3,6,2,1,0,2,3,29,null,0],["41987",2,"Byron Scott",1610612747,"LAL","Los Angeles Lakers","0048700037","1988-05-10","LAL vs. UTH","L",37,10,21,0.476,3,6,0.5,3,4,0.75,0,4,4,1,0,0,1,4,26,null,0],["41987",2,"Byron Scott",1610612747,"LAL","Los Angeles Lakers","0048700036","1988-05-08","LAL vs. UTH","W",33,8,16,0.5,0,2,0,2,2,1,3,1,4,3,0,0,3,0,18,null,0],["41987",2,"Byron Scott",1610612747,"LAL","Los Angeles Lakers","0048700020","1988-05-03","LAL @ SAN","W",32,4,11,0.364,0,0,null,1,1,1,1,2,3,1,0,0,6,3,9,null,0],["41987",2,"Byron Scott",1610612747,"LAL","Los Angeles Lakers","0048700016","1988-05-01","LAL vs. SAN","W",17,3,4,0.75,0,1,0,3,4,0.75,0,3,3,2,1,0,3,5,9,null,0],["41987",2,"Byron Scott",1610612747,"LAL","Los Angeles Lakers","0048700005","1988-04-29","LAL vs. SAN","W",34,7,12,0.583,2,2,1,3,3,1,3,1,4,3,5,0,3,4,19,null,0]]}]}