{"resource":"gamelogs","parameters":{"MeasureType":"Base","PerMode":"Totals","LeagueID":"00","SeasonYear":"1998-99","SeasonType":"Playoffs","PORound":0,"TeamID":null,"PlayerID":406,"Outcome":null,"Location":null,"Month":0,"SeasonSegment":null,"DateFrom":null,"DateTo":null,"OppTeamID":0,"VsConference":null,"VsDivision":null,"GameSegment":null,"Period":0,"ShotClockRange":null,"LastNGames":0},"resultSets":[{"name":"PlayerGameLogs","headers":["SEASON_YEAR","PLAYER_ID","PLAYER_NAME","TEAM_ID","TEAM_ABBREVIATION","TEAM_NAME","GAME_ID","GAME_DATE","MATCHUP","WL","MIN","FGM","FGA","FG_PCT","FG3M","FG3A","FG3_PCT","FTM","FTA","FT_PCT","OREB","DREB","REB","AST","TOV","STL","BLK","BLKA","PF","PFD","PTS","PLUS_MINUS","DD2","TD3","GP_RANK","W_RANK","L_RANK","W_PCT_RANK","MIN_RANK","FGM_RANK","FGA_RANK","FG_PCT_RANK","FG3M_RANK","FG3A_RANK","FG3_PCT_RANK","FTM_RANK","FTA_RANK","FT_PCT_RANK","OREB_RANK","DREB_RANK","REB_RANK","AST_RANK","TOV_RANK","STL_RANK","BLK_RANK","BLKA_RANK","PF_RANK","PFD_RANK","PTS_RANK","PLUS_MINUS_RANK","DD2_RANK","TD3_RANK"],"rowSet":[["1998-99",406,"Shaquille O'Neal",1610612747,"LAL","Los Angeles Lakers","0049800054","1999-05-23T00:00:00","LAL vs. SAS","L",45.111666666666665,12,23,0.522,0,0,0,12,23,0.522,8,6,14,0,1,1,1,1,5,0,36,-6,1,0,1,4,4,4,1,2,1,5,1,1,1,1,1,2,1,4,3,6,7,3,7,3,7,2,2,5,1,1],["1998-99",406,"Shaquille O'Neal",1610612747,"LAL","Los Angeles Lakers","0049800051","1999-05-22T00:00:00","LAL vs. SAS","L",36.88333333333333,8,14,0.571,0,0,0,6,14,0.429,7,8,15,0,2,0,3,1,3,1,22,-16,1,0,1,4,4,4,6,6,7,3,1,1,1,5,4,6,2,1,1,6,3,6,4,3,3,1,6,8,1,1],["1998-99",406,"Shaquille O'Neal",1610612747,"LAL","Los Angeles Lakers","0049800046","1999-05-19T00:00:00","LAL @ SAS","L",34.08166666666666,7,11,0.636,0,0,0,2,10,0.2,4,4,8,2,4,2,2,0,4,0,16,-8,0,0,1,4,4,4,7,7,8,1,1,1,1,8,7,8,7,8,8,4,1,1,6,1,4,2,8,7,7,1],["1998-99",406,"Shaquille O'Neal",1610612747,"LAL","Los Angeles Lakers","0049800042","1999-05-17T00:00:00","LAL @ SAS","L",39.916666666666664,6,19,0.316,0,0,0,9,14,0.643,7,8,15,0,2,1,1,6,5,0,21,1,1,0,1,4,4,4,5,8,6,8,1,1,1,2,4,1,2,1,1,6,3,3,7,8,7,2,7,4,1,1],["1998-99",406,"Shaquille O'Neal",1610612747,"LAL","Los Angeles Lakers","0049800032","1999-05-15T00:00:00","LAL @ HOU","W",43.1,14,22,0.636,0,0,0,9,18,0.5,5,6,11,3,2,0,3,2,2,0,37,11,1,0,1,1,1,1,2,1,3,1,1,1,1,2,2,3,5,4,4,3,3,6,4,7,1,2,1,2,1,1],["1998-99",406,"Shaquille O'Neal",1610612747,"LAL","Los Angeles Lakers","0049800024","1999-05-13T00:00:00","LAL @ HOU","L",42.04333333333334,9,22,0.409,0,0,0,8,16,0.5,5,5,10,2,1,1,4,0,2,0,26,-6,1,0,1,4,4,4,3,5,3,7,1,1,1,4,3,3,5,6,6,4,7,3,2,1,1,2,5,5,1,1],["1998-99",406,"Shaquille O'Neal",1610612747,"LAL","Los Angeles Lakers","0049800016","1999-05-11T00:00:00","LAL vs. HOU","W",33.43333333333333,12,21,0.571,0,0,0,4,9,0.444,2,7,9,7,2,0,5,1,4,0,28,20,0,0,1,1,1,1,8,2,5,3,1,1,1,7,8,5,8,3,7,1,3,6,1,3,4,2,3,1,7,1],["1998-99",406,"Shaquille O'Neal",1610612747,"LAL","Los Angeles Lakers","0049800007","1999-05-09T00:00:00","LAL vs. HOU","W",40.81666666666667,11,23,0.478,0,0,0,5,14,0.357,6,5,11,4,4,2,4,1,4,0,27,6,1,0,1,1,1,1,4,4,1,6,1,1,1,6,4,7,4,6,4,2,1,1,2,3,4,2,4,3,1,1]]}]}