{"resource":"gamelogs","parameters":{"MeasureType":"Base","PerMode":"Totals","LeagueID":"00","SeasonYear":"1970-71","SeasonType":"Playoffs","PORound":0,"TeamID":null,"PlayerID":76233,"Outcome":null,"Location":null,"Month":0,"SeasonSegment":null,"DateFrom":null,"DateTo":null,"OppTeamID":0,"VsConference":null,"VsDivision":null,"GameSegment":null,"Period":0,"ShotClockRange":null,"LastNGames":0},"resultSets":[{"name":"PlayerGameLogs","headers":["SEASON_ID","PLAYER_ID","PLAYER_NAME","TEAM_ID","TEAM_ABBREVIATION","TEAM_NAME","GAME_ID","GAME_DATE","MATCHUP","WL","MIN","FGM","FGA","FG_PCT","FG3M","FG3A","FG3_PCT","FTM","FTA","FT_PCT","OREB","DREB","REB","AST","STL","BLK","TOV","PF","PTS","PLUS_MINUS","VIDEO_AVAILABLE"],"rowSet":[["41970",76233,"Bill Bradley",1610612752,"NYK","New York Knicks","0047000317","1971-04-19","NYK vs. BLT","L",0,6,null,null,null,null,null,1,2,0.5,null,null,null,null,null,null,null,null,13,null,0],["41970",76233,"Bill Bradley",1610612752,"NYK","New York Knicks","0047000316","1971-04-18","NYK @ BLT","L",0,2,null,null,null,null,null,3,6,0.5,null,null,null,null,null,null,null,null,7,null,0],["41970",76233,"Bill Bradley",1610612752,"NYK","New York Knicks","0047000315","1971-04-16","NYK vs. BLT","W",0,7,null,null,null,null,null,2,2,1,null,null,null,null,null,null,null,null,16,null,0],["41970",76233,"Bill Bradley",1610612752,"NYK","New York Knicks","0047000314","1971-04-14","NYK @ BLT","L",0,5,null,null,null,null,null,0,0,null,null,null,null,null,null,null,null,null,10,null,0],["41970",76233,"Bill Bradley",1610612752,"NYK","New York Knicks","0047000313","1971-04-11","NYK @ BLT","L",0,2,null,null,null,null,null,0,0,null,null,null,null,null,null,null,null,null,4,null,0],["41970",76233,"Bill Bradley",1610612752,"NYK","New York Knicks","0047003002","1971-04-09","NYK vs. BLT","W",0,3,null,null,null,null,null,0,0,null,null,null,null,null,null,null,null,null,6,null,0],["41970",76233,"Bill Bradley",1610612752,"NYK","New York Knicks","0047000002","1971-04-06","NYK vs. BLT","W",0,7,null,null,null,null,null,1,1,1,null,null,null,null,null,null,null,null,15,null,0],["41970",76233,"Bill Bradley",1610612752,"NYK","New York Knicks","0047000245","1971-04-01","NYK vs. ATL","W",0,0,null,null,null,null,null,3,3,1,null,null,null,null,null,null,null,null,3,null,0],["41970",76233,"Bill Bradley",1610612752,"NYK","New York Knicks","0047000244","1971-03-30","NYK @ ATL","W",0,4,null,null,null,null,null,1,2,0.5,null,null,null,null,null,null,null,null,9,null,0],["41970",76233,"Bill Bradley",1610612752,"NYK","New York Knicks","0047000243","1971-03-28","NYK @ ATL","W",0,5,null,null,null,null,null,0,0,null,null,null,null,null,null,null,null,null,10,null,0],["41970",76233,"Bill Bradley",1610612752,"NYK","New York Knicks","0047003001","1971-03-27","NYK vs. ATL","L",0,3,null,null,null,null,null,2,2,1,null,null,null,null,null,null,null,null,8,null,0],["41970",76233,"Bill Bradley",1610612752,"NYK","New York Knicks","0047000241","1971-03-25","NYK vs. ATL","W",0,12,null,null,null,null,null,1,1,1,null,null,null,null,null,null,null,null,25,null,0]]}]}