{"resource":"gamelogs","parameters":{"MeasureType":"Base","PerMode":"Totals","LeagueID":"00","SeasonYear":"1971-72","SeasonType":"Playoffs","PORound":0,"TeamID":null,"PlayerID":76375,"Outcome":null,"Location":null,"Month":0,"SeasonSegment":null,"DateFrom":null,"DateTo":null,"OppTeamID":0,"VsConference":null,"VsDivision":null,"GameSegment":null,"Period":0,"ShotClockRange":null,"LastNGames":0},"resultSets":[{"name":"PlayerGameLogs","headers":["SEASON_ID","PLAYER_ID","PLAYER_NAME","TEAM_ID","TEAM_ABBREVIATION","TEAM_NAME","GAME_ID","GAME_DATE","MATCHUP","WL","MIN","FGM","FGA","FG_PCT","FG3M","FG3A","FG3_PCT","FTM","FTA","FT_PCT","OREB","DREB","REB","AST","STL","BLK","TOV","PF","PTS","PLUS_MINUS","VIDEO_AVAILABLE"],"rowSet":[["41971",76375,"Wilt Chamberlain",1610612747,"LAL","Los Angeles Lakers","0047100405","1972-05-07","LAL vs. NYK","W",47,10,14,0.714,null,null,null,4,9,0.444,null,null,29,4,null,null,null,2,24,null,0],["41971",76375,"Wilt Chamberlain",1610612747,"LAL","Los Angeles Lakers","0047103003","1972-05-05","LAL @ NYK","W",53,5,11,0.455,null,null,null,2,5,0.4,null,null,24,3,null,null,null,5,12,null,0],["41971",76375,"Wilt Chamberlain",1610612747,"LAL","Los Angeles Lakers","0047100413","1972-05-03","LAL @ NYK","W",48,9,10,0.9,null,null,null,8,11,0.727,null,null,20,1,null,null,null,4,26,null,0],["41971",76375,"Wilt Chamberlain",1610612747,"LAL","Los Angeles Lakers","0047100412","1972-04-30","LAL vs. NYK","W",48,10,19,0.526,null,null,null,3,7,0.429,null,null,24,4,null,null,null,3,23,null,0],["41971",76375,"Wilt Chamberlain",1610612747,"LAL","Los Angeles Lakers","0047100401","1972-04-26","LAL vs. NYK","L",40,5,11,0.455,null,null,null,2,3,0.667,null,null,19,1,null,null,null,4,12,null,0],["41971",76375,"Wilt Chamberlain",1610612747,"LAL","Los Angeles Lakers","0047100316","1972-04-22","LAL @ MIL","W",0,8,null,null,null,null,null,4,7,0.571,null,null,null,null,null,null,null,null,20,null,0],["41971",76375,"Wilt Chamberlain",1610612747,"LAL","Los Angeles Lakers","0047100315","1972-04-18","LAL vs. MIL","W",0,2,null,null,null,null,null,8,8,1,null,null,null,null,null,null,null,null,12,null,0],["41971",76375,"Wilt Chamberlain",1610612747,"LAL","Los Angeles Lakers","0047100314","1972-04-16","LAL @ MIL","L",0,2,null,null,null,null,null,1,8,0.125,null,null,null,null,null,null,null,null,5,null,0],["41971",76375,"Wilt Chamberlain",1610612747,"LAL","Los Angeles Lakers","0047100313","1972-04-14","LAL @ MIL","W",0,1,null,null,null,null,null,5,9,0.556,null,null,null,null,null,null,null,null,7,null,0],["41971",76375,"Wilt Chamberlain",1610612747,"LAL","Los Angeles Lakers","0047100312","1972-04-12","LAL vs. MIL","W",0,3,null,null,null,null,null,5,13,0.385,null,null,null,null,null,null,null,null,11,null,0],["41971",76375,"Wilt Chamberlain",1610612747,"LAL","Los Angeles Lakers","0047100311","1972-04-09","LAL vs. MIL","L",0,3,null,null,null,null,null,4,16,0.25,null,null,null,null,null,null,null,null,10,null,0],["41971",76375,"Wilt Chamberlain",1610612747,"LAL","Los Angeles Lakers","0047100224","1972-04-04","LAL @ CHI","W",0,4,null,null,null,null,null,0,3,0,null,null,null,null,null,null,null,null,8,null,0],["41971",76375,"Wilt Chamberlain",1610612747,"LAL","Los Angeles Lakers","0047100223","1972-04-02","LAL @ CHI","W",0,6,null,null,null,null,null,4,6,0.667,null,null,null,null,null,null,null,null,16,null,0],["41971",76375,"Wilt Chamberlain",1610612747,"LAL","Los Angeles Lakers","0047100222","1972-03-30","LAL vs. CHI","W",0,9,null,null,null,null,null,6,9,0.667,null,null,null,null,null,null,null,null,24,null,0],["41971",76375,"Wilt Chamberlain",1610612747,"LAL","Los Angeles Lakers","0047100221","1972-03-28","LAL vs. CHI","W",0,3,null,null,null,null,null,4,8,0.5,null,null,null,null,null,null,null,null,10,null,0]]}]}