{"resource":"gamelogs","parameters":{"MeasureType":"Base","PerMode":"Totals","LeagueID":"00","SeasonYear":"1977-78","SeasonType":"Playoffs","PORound":0,"TeamID":null,"PlayerID":76804,"Outcome":null,"Location":null,"Month":0,"SeasonSegment":null,"DateFrom":null,"DateTo":null,"OppTeamID":0,"VsConference":null,"VsDivision":null,"GameSegment":null,"Period":0,"ShotClockRange":null,"LastNGames":0},"resultSets":[{"name":"PlayerGameLogs","headers":["SEASON_ID","PLAYER_ID","PLAYER_NAME","TEAM_ID","TEAM_ABBREVIATION","TEAM_NAME","GAME_ID","GAME_DATE","MATCHUP","WL","MIN","FGM","FGA","FG_PCT","FG3M","FG3A","FG3_PCT","FTM","FTA","FT_PCT","OREB","DREB","REB","AST","STL","BLK","TOV","PF","PTS","PLUS_MINUS","VIDEO_AVAILABLE"],"rowSet":[["41977",76804,"George Gervin",1610612759,"SAN","San Antonio Spurs","0047700028","1978-04-28","SAN @ WAS","L",0,10,null,null,null,null,null,3,4,0.75,null,null,null,null,null,null,null,null,23,null,0],["41977",76804,"George Gervin",1610612759,"SAN","San Antonio Spurs","0047700025","1978-04-25","SAN vs. WAS","W",0,13,null,null,null,null,null,1,2,0.5,null,null,null,null,null,null,null,null,27,null,0],["41977",76804,"George Gervin",1610612759,"SAN","San Antonio Spurs","0047700023","1978-04-23","SAN @ WAS","L",0,12,null,null,null,null,null,11,17,0.647,null,null,null,null,null,null,null,null,35,null,0],["41977",76804,"George Gervin",1610612759,"SAN","San Antonio Spurs","0047700019","1978-04-21","SAN @ WAS","L",0,11,null,null,null,null,null,11,13,0.846,null,null,null,null,null,null,null,null,33,null,0],["41977",76804,"George Gervin",1610612759,"SAN","San Antonio Spurs","0047700015","1978-04-18","SAN vs. WAS","L",0,17,null,null,null,null,null,12,15,0.8,null,null,null,null,null,null,null,null,46,null,0],["41977",76804,"George Gervin",1610612759,"SAN","San Antonio Spurs","0047700009","1978-04-16","SAN vs. WAS","W",0,15,null,null,null,null,null,5,5,1,null,null,null,null,null,null,null,null,35,null,0]]}]}