{"resource":"gamelogs","parameters":{"MeasureType":"Base","PerMode":"Totals","LeagueID":"00","SeasonYear":"1977-78","SeasonType":"Playoffs","PORound":0,"TeamID":null,"PlayerID":77420,"Outcome":null,"Location":null,"Month":0,"SeasonSegment":null,"DateFrom":null,"DateTo":null,"OppTeamID":0,"VsConference":null,"VsDivision":null,"GameSegment":null,"Period":0,"ShotClockRange":null,"LastNGames":0},"resultSets":[{"name":"PlayerGameLogs","headers":["SEASON_ID","PLAYER_ID","PLAYER_NAME","TEAM_ID","TEAM_ABBREVIATION","TEAM_NAME","GAME_ID","GAME_DATE","MATCHUP","WL","MIN","FGM","FGA","FG_PCT","FG3M","FG3A","FG3_PCT","FTM","FTA","FT_PCT","OREB","DREB","REB","AST","STL","BLK","TOV","PF","PTS","PLUS_MINUS","VIDEO_AVAILABLE"],"rowSet":[["41977",77420,"Maurice Lucas",1610612757,"POR","Portland Trail Blazers","0047700032","1978-05-01","POR @ SEA","L",0,11,null,null,null,null,null,0,2,0,null,null,null,null,null,null,null,null,22,null,0],["41977",77420,"Maurice Lucas",1610612757,"POR","Portland Trail Blazers","0047700030","1978-04-30","POR vs. SEA","W",0,11,null,null,null,null,null,2,4,0.5,null,null,null,null,null,null,null,null,24,null,0],["41977",77420,"Maurice Lucas",1610612757,"POR","Portland Trail Blazers","0047700026","1978-04-26","POR @ SEA","L",0,9,null,null,null,null,null,2,2,1,null,null,null,null,null,null,null,null,20,null,0],["41977",77420,"Maurice Lucas",1610612757,"POR","Portland Trail Blazers","0047700022","1978-04-23","POR @ SEA","L",0,4,null,null,null,null,null,2,3,0.667,null,null,null,null,null,null,null,null,10,null,0],["41977",77420,"Maurice Lucas",1610612757,"POR","Portland Trail Blazers","0047700018","1978-04-21","POR vs. SEA","W",0,8,null,null,null,null,null,3,5,0.6,null,null,null,null,null,null,null,null,19,null,0],["41977",77420,"Maurice Lucas",1610612757,"POR","Portland Trail Blazers","0047700014","1978-04-18","POR vs. SEA","L",0,3,null,null,null,null,null,2,3,0.667,null,null,null,null,null,null,null,null,8,null,0]]}]}