{"resource":"gamelogs","parameters":{"MeasureType":"Base","PerMode":"Totals","LeagueID":"00","SeasonYear":"1955-56","SeasonType":"Playoffs","PORound":0,"TeamID":null,"PlayerID":77593,"Outcome":null,"Location":null,"Month":0,"SeasonSegment":null,"DateFrom":null,"DateTo":null,"OppTeamID":0,"VsConference":null,"VsDivision":null,"GameSegment":null,"Period":0,"ShotClockRange":null,"LastNGames":0},"resultSets":[{"name":"PlayerGameLogs","headers":["SEASON_ID","PLAYER_ID","PLAYER_NAME","TEAM_ID","TEAM_ABBREVIATION","TEAM_NAME","GAME_ID","GAME_DATE","MATCHUP","WL","MIN","FGM","FGA","FG_PCT","FG3M","FG3A","FG3_PCT","FTM","FTA","FT_PCT","OREB","DREB","REB","AST","STL","BLK","TOV","PF","PTS","PLUS_MINUS","VIDEO_AVAILABLE"],"rowSet":[["41955",77593,"Vern Mikkelsen",1610612747,"MNL","Minneapolis Lakers","0045500213","1956-03-21","MNL vs. STL","L",0,2,4,0.5,null,null,null,7,8,0.875,null,null,null,null,null,null,null,6,11,null,0],["41955",77593,"Vern Mikkelsen",1610612747,"MNL","Minneapolis Lakers","0045500212","1956-03-19","MNL vs. STL","W",0,3,null,null,null,null,null,4,null,null,null,null,null,null,null,null,null,2,10,null,0],["41955",77593,"Vern Mikkelsen",1610612747,"MNL","Minneapolis Lakers","0045500211","1956-03-17","MNL @ STL","L",0,6,null,null,null,null,null,7,8,0.875,null,null,null,null,null,null,null,6,19,null,0]]}]}