{"resource":"gamelogs","parameters":{"MeasureType":"Base","PerMode":"Totals","LeagueID":"00","SeasonYear":"1959-60","SeasonType":"Playoffs","PORound":0,"TeamID":null,"PlayerID":77907,"Outcome":null,"Location":null,"Month":0,"SeasonSegment":null,"DateFrom":null,"DateTo":null,"OppTeamID":0,"VsConference":null,"VsDivision":null,"GameSegment":null,"Period":0,"ShotClockRange":null,"LastNGames":0},"resultSets":[{"name":"PlayerGameLogs","headers":["SEASON_ID","PLAYER_ID","PLAYER_NAME","TEAM_ID","TEAM_ABBREVIATION","TEAM_NAME","GAME_ID","GAME_DATE","MATCHUP","WL","MIN","FGM","FGA","FG_PCT","FG3M","FG3A","FG3_PCT","FTM","FTA","FT_PCT","OREB","DREB","REB","AST","STL","BLK","TOV","PF","PTS","PLUS_MINUS","VIDEO_AVAILABLE"],"rowSet":[["41959",77907,"Frank Ramsey",1610612738,"BOS","Boston Celtics","0045900417","1960-04-09","BOS vs. STL","W",0,11,20,0.55,null,null,null,2,3,0.667,null,null,null,null,null,null,null,5,24,null,0],["41959",77907,"Frank Ramsey",1610612738,"BOS","Boston Celtics","0045900416","1960-04-07","BOS @ STL","L",0,4,15,0.267,null,null,null,4,4,1,null,null,null,null,null,null,null,4,12,null,0],["41959",77907,"Frank Ramsey",1610612738,"BOS","Boston Celtics","0045900415","1960-04-05","BOS vs. STL","W",0,4,9,0.444,null,null,null,3,4,0.75,null,null,null,null,null,null,null,5,11,null,0],["41959",77907,"Frank Ramsey",1610612738,"BOS","Boston Celtics","0045900414","1960-04-03","BOS @ STL","L",0,7,16,0.438,null,null,null,6,9,0.667,null,null,null,null,null,null,null,6,20,null,0],["41959",77907,"Frank Ramsey",1610612738,"BOS","Boston Celtics","0045900413","1960-04-02","BOS @ STL","W",0,10,15,0.667,null,null,null,4,5,0.8,null,null,null,null,null,null,null,4,24,null,0],["41959",77907,"Frank Ramsey",1610612738,"BOS","Boston Celtics","0045900412","1960-03-29","BOS vs. STL","L",0,5,16,0.313,null,null,null,7,8,0.875,null,null,null,null,null,null,null,3,17,null,0],["41959",77907,"Frank Ramsey",1610612738,"BOS","Boston Celtics","0045900411","1960-03-27","BOS vs. STL","W",0,8,11,0.727,null,null,null,5,5,1,null,null,null,null,null,null,null,2,21,null,0],["41959",77907,"Frank Ramsey",1610612738,"BOS","Boston Celtics","0045900326","1960-03-24","BOS @ PHW","W",0,5,null,null,null,null,null,4,4,1,null,null,null,null,null,null,null,3,14,null,0],["41959",77907,"Frank Ramsey",1610612738,"BOS","Boston Celtics","0045900325","1960-03-22","BOS vs. PHW","L",0,4,null,null,null,null,null,7,null,null,null,null,null,null,null,null,null,6,15,null,0],["41959",77907,"Frank Ramsey",1610612738,"BOS","Boston Celtics","0045900324","1960-03-20","BOS @ PHW","W",0,7,null,null,null,null,null,5,6,0.833,null,null,null,null,null,null,null,4,19,null,0],["41959",77907,"Frank Ramsey",1610612738,"BOS","Boston Celtics","0045900323","1960-03-19","BOS vs. PHW","W",0,4,null,null,null,null,null,2,2,1,null,null,null,null,null,null,null,null,10,null,0],["41959",77907,"Frank Ramsey",1610612738,"BOS","Boston Celtics","0045900322","1960-03-18","BOS @ PHW","L",0,8,null,null,null,null,null,3,null,null,null,null,null,null,null,null,null,5,19,null,0],["41959",77907,"Frank Ramsey",1610612738,"BOS","Boston Celtics","0045900321","1960-03-16","BOS vs. PHW","W",0,4,null,null,null,null,null,3,3,1,null,null,null,null,null,null,null,3,11,null,0]]}]}