{"resource":"gamelogs","parameters":{"MeasureType":"Base","PerMode":"Totals","LeagueID":"00","SeasonYear":"1960-61","SeasonType":"Playoffs","PORound":0,"TeamID":null,"PlayerID":78049,"Outcome":null,"Location":null,"Month":0,"SeasonSegment":null,"DateFrom":null,"DateTo":null,"OppTeamID":0,"VsConference":null,"VsDivision":null,"GameSegment":null,"Period":0,"ShotClockRange":null,"LastNGames":0},"resultSets":[{"name":"PlayerGameLogs","headers":["SEASON_ID","PLAYER_ID","PLAYER_NAME","TEAM_ID","TEAM_ABBREVIATION","TEAM_NAME","GAME_ID","GAME_DATE","MATCHUP","WL","MIN","FGM","FGA","FG_PCT","FG3M","FG3A","FG3_PCT","FTM","FTA","FT_PCT","OREB","DREB","REB","AST","STL","BLK","TOV","PF","PTS","PLUS_MINUS","VIDEO_AVAILABLE"],"rowSet":[["41960",78049,"Bill Russell",1610612738,"BOS","Boston Celtics","0046000415","1961-04-11","BOS vs. STL","W",48,9,17,0.529,null,null,null,12,17,0.706,null,null,38,null,null,null,null,2,30,null,0],["41960",78049,"Bill Russell",1610612738,"BOS","Boston Celtics","0046000414","1961-04-09","BOS @ STL","W",48,5,12,0.417,null,null,null,4,10,0.4,null,null,24,null,null,null,null,2,14,null,0],["41960",78049,"Bill Russell",1610612738,"BOS","Boston Celtics","0046000413","1961-04-08","BOS @ STL","L",48,10,18,0.556,null,null,null,4,13,0.308,null,null,23,null,null,null,null,3,24,null,0],["41960",78049,"Bill Russell",1610612738,"BOS","Boston Celtics","0046000412","1961-04-05","BOS vs. STL","W",48,2,11,0.182,null,null,null,1,3,0.333,null,null,28,null,null,null,null,4,5,null,0],["41960",78049,"Bill Russell",1610612738,"BOS","Boston Celtics","0046000411","1961-04-02","BOS vs. STL","W",41,7,19,0.368,null,null,null,1,4,0.25,null,null,31,null,null,null,null,2,15,null,0],["41960",78049,"Bill Russell",1610612738,"BOS","Boston Celtics","0046000325","1961-03-26","BOS vs. SYR","W",0,11,null,null,null,null,null,3,7,0.429,null,null,null,null,null,null,null,3,25,null,0],["41960",78049,"Bill Russell",1610612738,"BOS","Boston Celtics","0046000324","1961-03-25","BOS @ SYR","W",0,7,null,null,null,null,null,7,null,null,null,null,null,null,null,null,null,null,21,null,0],["41960",78049,"Bill Russell",1610612738,"BOS","Boston Celtics","0046000323","1961-03-23","BOS vs. SYR","W",0,8,null,null,null,null,null,2,null,null,null,null,null,null,null,null,null,0,18,null,0],["41960",78049,"Bill Russell",1610612738,"BOS","Boston Celtics","0046000322","1961-03-21","BOS @ SYR","L",0,6,null,null,null,null,null,5,9,0.556,null,null,null,null,null,null,null,3,17,null,0],["41960",78049,"Bill Russell",1610612738,"BOS","Boston Celtics","0046000321","1961-03-19","BOS vs. SYR","W",0,8,null,null,null,null,null,6,11,0.545,null,null,null,null,null,null,null,3,22,null,0]]}]}